{
    "pred_info": {
        "http://dbkwik.webdatacommons.org/Ultimate_Pop_Culture_Wik/property/developer": {
            "label": "developer",
            "r_resources": [],
            "resources": [
                "Microsoft"
            ]
        },
        "http://dbkwik.webdatacommons.org/Ultimate_Pop_Culture_Wik/property/generation": {
            "label": "generation",
            "r_resources": [],
            "resources": [
                "Seventh generation of video game consoles"
            ]
        },
        "http://dbkwik.webdatacommons.org/Ultimate_Pop_Culture_Wik/property/manufacturer": {
            "label": "manufacturer",
            "r_resources": [],
            "resources": [
                "Celestica",
                "Flextronics",
                "Foxconn",
                "Wistron Corporation"
            ]
        },
        "http://dbkwik.webdatacommons.org/Ultimate_Pop_Culture_Wik/property/media": {
            "label": "media",
            "r_resources": [],
            "resources": [
                "Compact disc",
                "DVD"
            ]
        },
        "http://dbkwik.webdatacommons.org/Ultimate_Pop_Culture_Wik/property/onlineservice": {
            "label": "onlineservice",
            "r_resources": [],
            "resources": [
                "Xbox Live"
            ]
        },
        "http://dbkwik.webdatacommons.org/Ultimate_Pop_Culture_Wik/property/operatingSystem": {
            "label": "operating system",
            "r_resources": [
                "PhysX"
            ],
            "resources": []
        },
        "http://dbkwik.webdatacommons.org/Ultimate_Pop_Culture_Wik/property/platform": {
            "label": "platform",
            "r_resources": [
                "Fox Engine"
            ],
            "resources": []
        },
        "http://dbkwik.webdatacommons.org/Ultimate_Pop_Culture_Wik/property/platforms": {
            "label": "platforms",
            "r_resources": [
                "Navbox/doc",
                "Assassin's Creed III",
                "Assassin's Creed IV: Black Flag",
                "Asura's Wrath: The Official Soundtrack",
                "Batman: Arkham Origins",
                "Capcom Versus",
                "Dead Space (series)",
                "Dead or Alive: Code Chronos",
                "Dead or Alive (series)",
                "Dead or Alive 4",
                "Dead or Alive 5",
                "Dead or Alive 5 Ultimate",
                "Dead or Alive Xtreme 2",
                "Devil May Cry (series)",
                "Devil May Cry 2",
                "Devil May Cry 3: Dante's Awakening",
                "Devil May Cry 4",
                "DmC: Devil May Cry",
                "Dragon Ball XenoVerse",
                "Dragon Ball Z: Burst Limit",
                "Final Fantasy (series)",
                "Mass Effect",
                "Mass Effect (series)",
                "Mass Effect 2",
                "Mass Effect 3",
                "Megami Tensei",
                "Metal Gear (video game)",
                "Metal Gear 2: Solid Snake",
                "Metal Gear Rising: Revengeance",
                "Metal Gear Solid: Peace Walker",
                "Metal Gear Solid HD Collection",
                "Metal Gear Solid V: Ground Zeroes",
                "Metal Gear Solid V: The Phantom Pain",
                "Persona (series)",
                "Prototype (series)",
                "Red Dead Redemption Original Soundtrack",
                "Red Dead Redemption: Undead Nightmare Original Soundtrack",
                "Resident Evil: Operation Raccoon City",
                "Resident Evil: Revelations",
                "Resident Evil 4",
                "Resident Evil 5",
                "Resident Evil 6",
                "Code: Veronica",
                "Sonic & All-Stars Racing Transformed",
                "Sonic Free Riders",
                "Street Fighter X Tekken",
                "Teenage Mutant Ninja Turtles: Out of the Shadows",
                "Tekken (series)",
                "Tekken X Street Fighter",
                "The Amazing Spider-Man (2012 video game)",
                "Tomb Raider (2013 video game)",
                "Tomb Raider (series)",
                "Virtua Fighter (series)"
            ],
            "resources": []
        },
        "http://dbkwik.webdatacommons.org/Ultimate_Pop_Culture_Wik/property/products": {
            "label": "products",
            "r_resources": [
                "Microsoft Studios (game studio)"
            ],
            "resources": []
        },
        "http://dbkwik.webdatacommons.org/Ultimate_Pop_Culture_Wik/property/type": {
            "label": "type",
            "r_resources": [],
            "resources": [
                "Video game console"
            ]
        }
    },
    "subj_basic_info": {
        "dbr": "http://dbpedia.org/resource/Xbox_360",
        "gender": "",
        "name": "Xbox 360",
        "types": "http://dbkwik.webdatacommons.org/Ultimate_Pop_Culture_Wik/ontology/Device|http://dbkwik.webdatacommons.org/Ultimate_Pop_Culture_Wik/ontology/InformationAppliance",
        "types_sents": [
            "a device",
            "an information appliance"
        ]
    }
}